Metadata-Version: 2.1
Name: aiida-quantumespresso-test
Version: 4.0.0a1
Summary: The official AiiDA plugin for Quantum ESPRESSO
Keywords: aiida,workflows
Author-email: The AiiDA team <developers@aiida.net>
Requires-Python: >=3.8
Classifier: Development Status :: 5 - Production/Stable
Classifier: Framework :: AiiDA
Classifier: License :: OSI Approved :: MIT License
Classifier: Programming Language :: Python
Classifier: Programming Language :: Python :: 3.8
Classifier: Programming Language :: Python :: 3.9
Classifier: Programming Language :: Python :: 3.10
Requires-Dist: aiida_core[atomic_tools]~=2.0
Requires-Dist: aiida-pseudo~=0.7.0
Requires-Dist: click~=8.0
Requires-Dist: importlib_resources
Requires-Dist: jsonschema
Requires-Dist: numpy
Requires-Dist: packaging
Requires-Dist: qe-tools~=2.0rc1
Requires-Dist: xmlschema~=1.2,>=1.2.5
Requires-Dist: sphinx~=4.1 ; extra == "docs"
Requires-Dist: sphinx-copybutton~=0.5.0 ; extra == "docs"
Requires-Dist: sphinx-book-theme~=0.3.2 ; extra == "docs"
Requires-Dist: sphinx-click~=4.0 ; extra == "docs"
Requires-Dist: pre-commit~=2.17 ; extra == "pre-commit"
Requires-Dist: pylint~=2.12.2 ; extra == "pre-commit"
Requires-Dist: pylint-aiida~=0.1.1 ; extra == "pre-commit"
Requires-Dist: toml ; extra == "pre-commit"
Requires-Dist: aiida-tcod ; extra == "tcod"
Requires-Dist: pgtest~=1.3 ; extra == "tests"
Requires-Dist: pytest~=6.0 ; extra == "tests"
Requires-Dist: pytest-regressions~=2.3 ; extra == "tests"
Project-URL: Documentation, https://aiida-quantumespresso.readthedocs.io
Project-URL: Home, https://github.com/aiidateam/aiida-quantumespresso
Project-URL: Source, https://github.com/aiidateam/aiida-quantumespresso
Provides-Extra: docs
Provides-Extra: pre-commit
Provides-Extra: tcod
Provides-Extra: tests
